nan/__entry__.py
nan/__init__.py
nan/__main__.py
nan-0.1.2.dist-info/LICENSE
nan-0.1.2.dist-info/METADATA
nan-0.1.2.dist-info/WHEEL
nan-0.1.2.dist-info/entry_points.txt
nan-0.1.2.dist-info/top_level.txt
nan-0.1.2.dist-info/RECORD
