Metadata-Version: 2.1
Name: nan
Version: 0.1.2
Summary: python client for neo node
Home-page: https://github.com/lazynode/NeoArchiveNode
Author: vang1ong7ang
Author-email: vang1ong7ang@outlook.com
License: MIT License
Project-URL: Bug Tracker, https://github.com/lazynode/NeoArchiveNode/issues
Platform: UNKNOWN
Classifier: Programming Language :: Python :: 3
Classifier: License :: OSI Approved :: MIT License
Classifier: Operating System :: OS Independent
Requires-Python: >=3.6
License-File: LICENSE
